boj/__init__.py
boj/classes/__init__.py
boj/classes/class_.py
boj/classes/database.py
boj/persistence/__init__.py
boj/persistence/databases.py
boj/persistence/entity.py
boj/problems/__init__.py
boj/problems/database.py
boj/problems/problem.py
boj/tags/__init__.py
boj/tags/database.py
boj/tags/tag.py
boj-0.2.0.dist-info/LICENSE
boj-0.2.0.dist-info/METADATA
boj-0.2.0.dist-info/WHEEL
boj-0.2.0.dist-info/top_level.txt
boj-0.2.0.dist-info/RECORD
