Metadata-Version: 2.1
Name: boj
Version: 0.2.0
Summary: BOJ Offline Judge
Author-email: Hepheir <hepheir@gmail.com>
Maintainer-email: Hepheir <hepheir@gmail.com>
License: GNU GENERAL PUBLIC LICENSE
Project-URL: Homepage, https://github.com/Hepheir/BOJ-Offline-Judge
Project-URL: Repository, https://github.com/Hepheir/BOJ-Offline-Judge
Project-URL: Issues, https://github.com/Hepheir/BOJ-Offline-Judge/issues
Project-URL: Changelog, https://github.com/hepheir/BOJ-Offline-Judge/blob/main/CHANGELOG.md
Keywords: boj
Classifier: Development Status :: 1 - Planning
Classifier: License :: OSI Approved :: GNU General Public License v3 (GPLv3)
Classifier: Natural Language :: Korean
Classifier: Operating System :: OS Independent
Classifier: Programming Language :: Python :: 3.7
Classifier: Topic :: Utilities
Classifier: Typing :: Typed
Requires-Python: >=3.7.9
License-File: LICENSE
Requires-Dist: beautifulsoup4 >=4.12.3
Requires-Dist: requests >=2.31.0
